fastzdp_login/__init__.py
fastzdp_login/jwt_util.py
fastzdp_login/passlib_util.py
fastzdp_login/user_model.py
fastzdp_login/user_router.py
fastzdp_login/user_schema.py
fastzdp_login-0.1.5.dist-info/LICENSE
fastzdp_login-0.1.5.dist-info/METADATA
fastzdp_login-0.1.5.dist-info/WHEEL
fastzdp_login-0.1.5.dist-info/RECORD
