Metadata-Version: 2.1
Name: fastzdp-login
Version: 0.1.5
Summary: 专为Fast API打造的用户登录注册相关功能的微代码框架
License: Apache-2.0
Author: zhangdapeng
Requires-Python: >=3.12,<4.0
Classifier: License :: OSI Approved :: Apache Software License
Classifier: Programming Language :: Python :: 3
Classifier: Programming Language :: Python :: 3.12
Requires-Dist: fastzdp-api (>=0.1.5,<0.2.0)
Requires-Dist: fastzdp-redis (>=0.1.0,<0.2.0)
Requires-Dist: passlib (>=1.7.4,<2.0.0)
Requires-Dist: pyjwt (>=2.8.0,<3.0.0)
